pythonbook20200311/__init__.py
pythonbook20200311/data/data_file
pythonbook20200311-1.0.0.dist-info/LICENSE.txt
pythonbook20200311-1.0.0.dist-info/METADATA
pythonbook20200311-1.0.0.dist-info/WHEEL
pythonbook20200311-1.0.0.dist-info/top_level.txt
pythonbook20200311-1.0.0.dist-info/RECORD
